thinkgear/__init__.py
thinkgear/bluetooth.py
thinkgear/data_points.py
thinkgear/discover.py
thinkgear/parser.py
thinkgear/serial.py
thinkgear/test_think_gear.py
thinkgear/think_gear.py
thinkgear_py3-2.3.dist-info/LICENSE
thinkgear_py3-2.3.dist-info/METADATA
thinkgear_py3-2.3.dist-info/WHEEL
thinkgear_py3-2.3.dist-info/top_level.txt
thinkgear_py3-2.3.dist-info/RECORD
