Metadata-Version: 2.2
Name: thinkgear-py3
Version: 2.3
Summary: ThinkGear Serial Stream Protocol implementation
Home-page: https://github.com/gaurapanasenko/python3-thinkgear
Author: Yehor Panasenko
Author-email: gaura.panasenko@gmail.com
License-File: LICENSE
Dynamic: author
Dynamic: author-email
Dynamic: description
Dynamic: description-content-type
Dynamic: home-page
Dynamic: summary
